binlets/__init__.py
binlets/_binlets.py
binlets/_modwt.py
binlets/tests/test_binlet.py
binlets/tests/test_modwt.py
binlets-1.0.0.dist-info/LICENSE
binlets-1.0.0.dist-info/METADATA
binlets-1.0.0.dist-info/WHEEL
binlets-1.0.0.dist-info/top_level.txt
binlets-1.0.0.dist-info/RECORD
