Metadata-Version: 2.1
Name: binlets
Version: 1.0.0
Summary: Denoising via adaptive binning.
Author-email: Mauro Silberberg <maurosilber@gmail.com>
License: MIT License
Project-URL: Homepage, https://github.com/maurosilber/binlets
Project-URL: Bug Tracker, https://github.com/maurosilber/binlets/issues
Keywords: denoising,adaptive,wavelets
Classifier: Programming Language :: Python :: 3
Classifier: License :: OSI Approved :: MIT License
Classifier: Operating System :: OS Independent
Classifier: Intended Audience :: Developers
Classifier: Intended Audience :: Science/Research
Classifier: Topic :: Scientific/Engineering
Classifier: Topic :: Software Development :: Libraries
Requires-Python: >=3.7
License-File: LICENSE
Requires-Dist: numpy
Requires-Dist: typing-extensions ; python_version < "3.8"
Provides-Extra: test
Requires-Dist: pytest ; extra == 'test'
Requires-Dist: hypothesis ; extra == 'test'
Requires-Dist: scipy ; extra == 'test'
